{
  "users": [
    {
      "username": "Admin",
      "email": "samvel1973@seznam.cz",
      "password": "Admin123@",
      "id": "d1f1"
    },
    {
      "id": "c05c",
      "username": "Tom",
      "email": "samvel11973@seznam.cz",
      "password": "asd@sadf12333",
      "isBlocked": false
    },
    {
      "id": "647b",
      "username": "Cruze",
      "email": "samvel1921373@seznam.cz",
      "password": "asd@#34SD",
      "isBlocked": false
    }
  ],
  "KarateTutorial": [
    {
      "id": "67a2",
      "title": "Tutor1",
      "description": "sdvgvgsdv",
      "body": "IHHBJKvhjbklnk.;mhvjcgvfgbhl;oiluvflhi;kbg\nsdvsdv\nsdvsd\nvsdv\nsdv\nsdvsdvsdvbgdb"
    },
    {
      "id": "7433",
      "title": "Tutor112",
      "description": "sdvgvgsdvwdsfcvsa",
      "body": "IHHBJKvhjbklnk.;mhvjcgvfgbhl;oiluvflhi;kbg\nsdvsdv\nsdvsdasdv\nvsdv\nsdv\nsdvsdvsdvbgdb"
    },
    {
      "id": "3381",
      "title": "Tutor11211",
      "description": "sdvgvgsdvwdsfcvsa",
      "body": "IHHBJKvhjbklnk.;mhvjcgvfgbhl;oiluvflhi;kbg\nsdvsdv\nsdvsdasdv\nvsdv\nsdv\nsdvsdvsdvbgdb"
    },
    {
      "id": "e41a",
      "title": "Tutor11211qefeew",
      "description": "sdvgvgsdvwdsfcvsa",
      "body": "IHHBJKvhjbklnk.;mhvjcgvfgbhl;oiluvflhi;kbg\nsdvsdv\nsdvsdasdv\nvsdv\nsdv\nsdvsdvsdvbgdb"
    },
    {
      "id": "ff14",
      "title": "Tutor11211qefeew",
      "description": "sdvgvgsdvwdsfcvsasdvsdv",
      "body": "IHHBJKvhjbklnk.;mhvjcgvfgbhl;oiluvflhi;kbg\nsdvsdv\nsdvsdasdv\nvsdv\nsdv\nsdvsdvsdvbgdb"
    }
  ]
}